odoo/addons/partner_contact_personal_information_page/README.rst
odoo/addons/partner_contact_personal_information_page/__init__.py
odoo/addons/partner_contact_personal_information_page/__manifest__.py
odoo/addons/partner_contact_personal_information_page/i18n/ca.po
odoo/addons/partner_contact_personal_information_page/i18n/da.po
odoo/addons/partner_contact_personal_information_page/i18n/de.po
odoo/addons/partner_contact_personal_information_page/i18n/es.po
odoo/addons/partner_contact_personal_information_page/i18n/fi.po
odoo/addons/partner_contact_personal_information_page/i18n/fr.po
odoo/addons/partner_contact_personal_information_page/i18n/hr.po
odoo/addons/partner_contact_personal_information_page/i18n/hr_HR.po
odoo/addons/partner_contact_personal_information_page/i18n/hu.po
odoo/addons/partner_contact_personal_information_page/i18n/it.po
odoo/addons/partner_contact_personal_information_page/i18n/nl.po
odoo/addons/partner_contact_personal_information_page/i18n/partner_contact_personal_information_page.pot
odoo/addons/partner_contact_personal_information_page/i18n/pt.po
odoo/addons/partner_contact_personal_information_page/i18n/pt_BR.po
odoo/addons/partner_contact_personal_information_page/i18n/pt_PT.po
odoo/addons/partner_contact_personal_information_page/i18n/sl.po
odoo/addons/partner_contact_personal_information_page/readme/CONTRIBUTORS.md
odoo/addons/partner_contact_personal_information_page/readme/DESCRIPTION.md
odoo/addons/partner_contact_personal_information_page/readme/USAGE.md
odoo/addons/partner_contact_personal_information_page/static/description/icon.png
odoo/addons/partner_contact_personal_information_page/static/description/index.html
odoo/addons/partner_contact_personal_information_page/views/res_partner.xml
odoo_addon_partner_contact_personal_information_page-19.0.1.0.0.2.dist-info/METADATA
odoo_addon_partner_contact_personal_information_page-19.0.1.0.0.2.dist-info/WHEEL
odoo_addon_partner_contact_personal_information_page-19.0.1.0.0.2.dist-info/top_level.txt
odoo_addon_partner_contact_personal_information_page-19.0.1.0.0.2.dist-info/RECORD
