Metadata-Version: 2.1
Name: odoo-addon-partner_contact_personal_information_page
Version: 19.0.1.0.0.2
Requires-Dist: odoo==19.0.*
Summary: Add a page to contacts form to put personal information
Home-page: https://github.com/OCA/partner-contact
License: AGPL-3
Author: Nicolas JEUDY,Odoo Community Association (OCA)
Author-email: support@odoo-community.org
Classifier: Programming Language :: Python
Classifier: Framework :: Odoo
Classifier: Framework :: Odoo :: 19.0
Classifier: License :: OSI Approved :: GNU Affero General Public License v3
